oarepo_profiler/__init__.py
oarepo_profiler/version.py
tests/__init__.py
tests/test_version.py
oarepo_profiler-1.0.1.dist-info/AUTHORS.rst
oarepo_profiler-1.0.1.dist-info/LICENSE
oarepo_profiler-1.0.1.dist-info/METADATA
oarepo_profiler-1.0.1.dist-info/WHEEL
oarepo_profiler-1.0.1.dist-info/top_level.txt
oarepo_profiler-1.0.1.dist-info/RECORD
