Metadata-Version: 2.1
Name: oarepo-profiler
Version: 1.0.1
Summary: Data model for PIGA KROKD repository
Home-page: https://github.com/oarepo/oarepo-profiler
Author: CIS UCT Prague
Author-email: simeki@vscht.cz
License: MIT
Keywords: Invenio profiler
Platform: any
Classifier: Environment :: Web Environment
Classifier: Intended Audience :: Developers
Classifier: License :: OSI Approved :: MIT License
Classifier: Operating System :: OS Independent
Classifier: Programming Language :: Python
Classifier: Topic :: Internet :: WWW/HTTP :: Dynamic Content
Classifier: Topic :: Software Development :: Libraries :: Python Modules
Classifier: Programming Language :: Python :: 2
Classifier: Programming Language :: Python :: 2.7
Classifier: Programming Language :: Python :: 3
Classifier: Programming Language :: Python :: 3.5
Classifier: Development Status :: 4 - Beta
Provides-Extra: tests
Requires-Dist: oarepo[tests] (~=3.1.1) ; extra == 'tests'
Provides-Extra: tests-es7
Requires-Dist: oarepo[tests-es7] (~=3.1.1) ; extra == 'tests-es7'
